ytt_py_utils/__init__.py
ytt_py_utils/config/__init__.py
ytt_py_utils/config/abstract.py
ytt_py_utils/config/yaml/__init__.py
ytt_py_utils/config/yaml/parser.py
ytt_py_utils/config/yaml/bkp/template_config.yaml
ytt_py_utils/env/__init__.py
ytt_py_utils/env/envs.py
ytt_py_utils/err/__init__.py
ytt_py_utils/err/errors.py
ytt_py_utils/img/__init__.py
ytt_py_utils/img/Pillow/__init__.py
ytt_py_utils/img/Pillow/image.py
ytt_py_utils/img/Pillow/settings
ytt_py_utils/img/Pillow/ressources/eye_open.png
ytt_py_utils/log/__init__.py
ytt_py_utils/log/logs.py
ytt_py_utils/log/logs_conf.yaml
ytt_py_utils/ui/__init__.py
ytt_py_utils/ui/Pyside2/__init__.py
ytt_py_utils/ui/Pyside2/buttons.py
ytt_py_utils/ui/Pyside2/core.py
ytt_py_utils/ui/Pyside2/others.py
ytt_py_utils/ui/Pyside2/text.py
ytt_py_utils/web/__init__.py
ytt_py_utils/web/request.py
ytt_py_utils-1.0.0.dist-info/METADATA
ytt_py_utils-1.0.0.dist-info/WHEEL
ytt_py_utils-1.0.0.dist-info/licenses/LICENSE
ytt_py_utils-1.0.0.dist-info/RECORD
