Metadata-Version: 2.1
Name: ytt_py_utils
Version: 1.0.0
Summary: Some misc python utils 
Project-URL: Homepage, https://github.com/dzertus/ytt_utils
Author-email: youssef taktak <youssef.taktak@hotmail.fr>
License-File: LICENSE
Classifier: License :: OSI Approved :: MIT License
Classifier: Operating System :: OS Independent
Classifier: Programming Language :: Python :: 3
Requires-Python: >=3.9
